SEM_3/DSD_LAB/Week0/Example.v
// Example
module Example(x1, x2, x3, f);
input x1, x2, x3;
output f;
and (g, x1, x2);
not (k, x2);
and (h, k, x3);
or (f, g, h);
endmodule

SEM_3/DSD_LAB/Week0/Example_tb.v
//Test Bench
`timescale 1ns/1ns	//incl time 
`include "Example.v"	//Name of the Design
module Example_tb();	//Name of test bench
reg x1, x2, x3; //input
wire f; //output
Example ex1(x1, x2, x3, f);	//ex1 -> name of the gate, can make more instances
initial
begin
$dumpfile("Example_tb.vcd");
$dumpvars(0, Example_tb);
x1 = 1'b0; x2 = 1'b0; x3 = 1'b0;
#20
x1 = 1'b0; x2 = 1'b0; x3 = 1'b1;
#20
x1 = 1'b0; x2 = 1'b1; x3 = 1'b0;
#20
x1 = 1'b0; x2 = 1'b1; x3 = 1'b1;
#20
x1 = 1'b1; x2 = 1'b0; x3 = 1'b0;
#20
x1 = 1'b1; x2 = 1'b0; x3 = 1'b1;
#20
x1 = 1'b1; x2 = 1'b1; x3 = 1'b0;
#20
x1 = 1'b1; x2 = 1'b1; x3 = 1'b1;
#20
$display("Done");
end
endmodule

SEM_3/DSD_LAB/Week0/Example_tb.vcd
$date
	Wed Jul 24 15:20:56 2024
$end
$version
	Icarus Verilog
$end
$timescale
	1ns
$end
$scope module Example_tb $end
$var wire 1 ! f $end
$var reg 1 " x1 $end
$var reg 1 # x2 $end
$var reg 1 $ x3 $end
$scope module ex1 $end
$var wire 1 ! f $end
$var wire 1 % g $end
$var wire 1 & h $end
$var wire 1 ' k $end
$var wire 1 " x1 $end
$var wire 1 # x2 $end
$var wire 1 $ x3 $end
$upscope $end
$upscope $end
$enddefinitions $end
#0
$dumpvars
1'
0&
0%
0$
0#
0"
0!
$end
#20
1!
1&
1$
#40
0!
0&
0'
0$
1#
#60
1$
#80
1'
0$
0#
1"
#100
1!
1&
1$
#120
0&
1%
0'
0$
1#
#140
1$
