SEM_3/DSD_LAB/Week5/Function_Decoder4to16.v
/*Q3 - Implement the function, F(a, b, c, d) = Σm (2,3,4,5,6,7,10,11,12,15) using a 4 to 16 binary decoder and an OR gate.*/
module Function_Decoder4to16 (A, B, C, D, f);
input A, B, C, D;
output f;

reg [15:0] Y;
always@(*) begin
   for (integer k = 0; k < 16; k += 1) begin
     if ({A, B, C, D} == k)
       Y[k] = 1;
     else
       Y[k] = 0;
   end
end

assign f = Y[2] | Y[3] | Y[4] | Y[5] | Y[6] | Y[7] | Y[10] | Y[11] | Y[12] | Y[15];

endmodule

SEM_3/DSD_LAB/Week5/Function_Decoder4to16_tb.v
//Test bench
`timescale 1ns/1ns
`include "Function_Decoder4to16.v"
module Function_Decoder4to16_tb();
reg A, B, C, D;
wire f;
//wire [15:0] Y;
Function_Decoder4to16 mu(A, B, C, D, f);
initial
begin
 $dumpfile("Function_Decoder4to16_tb.vcd");
 $dumpvars(0, Function_Decoder4to16_tb);
 for (integer i=0; i<16; i++)
 begin
   {A, B, C, D} = i;
   #10;
 end
 $display("Done");
end
endmodule

SEM_3/DSD_LAB/Week5/Function_Decoder4to16_tb.vcd
$date
	Wed Aug 28 16:04:53 2024
$end
$version
	Icarus Verilog
$end
$timescale
	1ns
$end
$scope module Function_Decoder4to16_tb $end
$var wire 1 ! f $end
$var reg 1 " A $end
$var reg 1 # B $end
$var reg 1 $ C $end
$var reg 1 % D $end
$scope module mu $end
$var wire 1 " A $end
$var wire 1 # B $end
$var wire 1 $ C $end
$var wire 1 % D $end
$var wire 1 ! f $end
$var reg 16 & Y [15:0] $end
$scope begin $ivl_for_loop0 $end
$var integer 32 ' k [31:0] $end
$upscope $end
$upscope $end
$scope begin $ivl_for_loop1 $end
$var integer 32 ( i [31:0] $end
$upscope $end
$upscope $end
$enddefinitions $end
#0
$dumpvars
b0 (
b10000 '
b1 &
0%
0$
0#
0"
0!
$end
#10
b10 &
b10000 '
1%
b1 (
#20
1!
b100 &
b10000 '
1$
0%
b10 (
#30
b1000 &
b10000 '
1%
b11 (
#40
b10000 &
b10000 '
1#
0$
0%
b100 (
#50
b100000 &
b10000 '
1%
b101 (
#60
b1000000 &
b10000 '
1$
0%
b110 (
#70
b10000000 &
b10000 '
1%
b111 (
#80
0!
b100000000 &
b10000 '
1"
0#
0$
0%
b1000 (
#90
b1000000000 &
b10000 '
1%
b1001 (
#100
1!
b10000000000 &
b10000 '
1$
0%
b1010 (
#110
b100000000000 &
b10000 '
1%
b1011 (
#120
b1000000000000 &
b10000 '
1#
0$
0%
b1100 (
#130
0!
b10000000000000 &
b10000 '
1%
b1101 (
#140
b100000000000000 &
b10000 '
1$
0%
b1110 (
#150
1!
b1000000000000000 &
b10000 '
1%
b1111 (
#160
b10000 (
