SEM_3/DSD_LAB/Week5/Function_Mux4to1.v
/*Q1 - Implement the expression F(A,B,C,D)=∑m (0,1,2,4,6,9,12,14) using 4:1 multiplexer and
write the Verilog code for the same.*/
module Function_Mux4to1 (A, B, C, D, f);
input A, B, C, D;
output f;
wire [3:0] i;
assign i[0] = ~(C&D);
assign i[1] = ~D;
assign i[2] = ~C&D;
assign i[3] = ~D;

assign f = (A == 0)?((B == 0)?i[0]:i[1]):((B==0)?i[2]:i[3]);

endmodule

SEM_3/DSD_LAB/Week5/Function_Mux4to1_tb.v
//Test bench
`timescale 1ns/1ns
`include "Function_Mux4to1.v"
module Function_Mux4to1_tb ();
reg A, B, C, D;
wire f;
Function_Mux4to1 mu(A, B, C, D, f);
initial
begin
 $dumpfile("Function_Mux4to1_tb.vcd");
 $dumpvars(0, Function_Mux4to1_tb);
 for (integer i=0; i<16; i++)
 begin
   {A, B, C, D} = i;
   #10;
 end
 $display("Done");
end
endmodule

SEM_3/DSD_LAB/Week5/Function_Mux4to1_tb.vcd
$date
	Wed Aug 28 14:48:49 2024
$end
$version
	Icarus Verilog
$end
$timescale
	1ns
$end
$scope module Function_Mux4to1_tb $end
$var wire 1 ! f $end
$var reg 1 " A $end
$var reg 1 # B $end
$var reg 1 $ C $end
$var reg 1 % D $end
$scope module mu $end
$var wire 1 " A $end
$var wire 1 # B $end
$var wire 1 $ C $end
$var wire 1 % D $end
$var wire 4 & i [3:0] $end
$var wire 1 ! f $end
$upscope $end
$scope begin $ivl_for_loop0 $end
$var integer 32 ' i [31:0] $end
$upscope $end
$upscope $end
$enddefinitions $end
#0
$dumpvars
b0 '
b1011 &
0%
0$
0#
0"
1!
$end
#10
b101 &
1%
b1 '
#20
b1011 &
1$
0%
b10 '
#30
0!
b0 &
1%
b11 '
#40
1!
b1011 &
1#
0$
0%
b100 '
#50
0!
b101 &
1%
b101 '
#60
1!
b1011 &
1$
0%
b110 '
#70
0!
b0 &
1%
b111 '
#80
b1011 &
1"
0#
0$
0%
b1000 '
#90
1!
b101 &
1%
b1001 '
#100
0!
b1011 &
1$
0%
b1010 '
#110
b0 &
1%
b1011 '
#120
1!
b1011 &
1#
0$
0%
b1100 '
#130
0!
b101 &
1%
b1101 '
#140
1!
b1011 &
1$
0%
b1110 '
#150
0!
b0 &
1%
b1111 '
#160
b10000 '
