SEM_3/DSD_LAB/Week1/lab1a.v
// Q1 (a)
module lab1a(A, B, C, D, F);
input A, B, C, D;
output F;
assign F = (~A&~B)|(~B&~C)|(~C&~D);
endmodule

SEM_3/DSD_LAB/Week1/lab1a_tb.v
//Test Bench
`timescale 1ns/1ns
`include "lab1a.v"
module lab1a_tb();
reg A, B, C, D;
wire F;
lab1a l1(A, B, C, D, F);
initial
begin
$dumpfile("lab1a_tb.vcd");
$dumpvars(0, lab1a_tb);
A = 1'b0; B = 1'b0; C = 1'b0; D = 1'b0;
#20
A = 1'b0; B = 1'b0; C = 1'b0; D = 1'b1;
#20
A = 1'b0; B = 1'b0; C = 1'b1; D = 1'b0;
#20
A = 1'b0; B = 1'b0; C = 1'b1; D = 1'b1;
#20
A = 1'b0; B = 1'b1; C = 1'b0; D = 1'b0;
#20
A = 1'b0; B = 1'b1; C = 1'b0; D = 1'b1;
#20
A = 1'b0; B = 1'b1; C = 1'b1; D = 1'b0;
#20
A = 1'b0; B = 1'b1; C = 1'b1; D = 1'b1;
#20
A = 1'b1; B = 1'b0; C = 1'b0; D = 1'b0;
#20
A = 1'b1; B = 1'b0; C = 1'b0; D = 1'b1;
#20
A = 1'b1; B = 1'b0; C = 1'b1; D = 1'b0;
#20
A = 1'b1; B = 1'b0; C = 1'b1; D = 1'b1;
#20
A = 1'b1; B = 1'b1; C = 1'b0; D = 1'b0;
#20
A = 1'b1; B = 1'b1; C = 1'b0; D = 1'b1;
#20
A = 1'b1; B = 1'b1; C = 1'b1; D = 1'b0;
#20
A = 1'b1; B = 1'b1; C = 1'b1; D = 1'b1;
#20
$display("Done");
end
endmodule

SEM_3/DSD_LAB/Week1/lab1a_tb.vcd
$date
	Wed Jul 31 14:52:39 2024
$end
$version
	Icarus Verilog
$end
$timescale
	1ns
$end
$scope module lab1a_tb $end
$var wire 1 ! F $end
$var reg 1 " A $end
$var reg 1 # B $end
$var reg 1 $ C $end
$var reg 1 % D $end
$scope module l1 $end
$var wire 1 " A $end
$var wire 1 # B $end
$var wire 1 $ C $end
$var wire 1 % D $end
$var wire 1 ! F $end
$upscope $end
$upscope $end
$enddefinitions $end
#0
$dumpvars
0%
0$
0#
0"
1!
$end
#20
1%
#40
0%
1$
#60
1%
#80
0%
0$
1#
#100
0!
1%
#120
0%
1$
#140
1%
#160
1!
0%
0$
0#
1"
#180
1%
#200
0!
0%
1$
#220
1%
#240
1!
0%
0$
1#
#260
0!
1%
#280
0%
1$
#300
1%
