SEM_3/DSD_LAB/Week1/lab3.v
// Q3 (Additional 1)
module lab3(A, B, C, F1, F2);
input A, B, C;
output F1, F2;
assign F1 = (A&~C)|(B&C)|(~B&~C);
assign F2 = (A|~B|C)&(A|B|~C)&(~A|B|~C);
endmodule

SEM_3/DSD_LAB/Week1/lab3_tb.v
//Test Bench
`timescale 1ns/1ns
`include "lab3.v"
module lab3_tb();
reg A, B, C;
wire F1, F2;
lab3 l1(A, B, C, F1, F2);
initial begin
$dumpfile("lab3_tb.vcd");
$dumpvars(0, lab3_tb);
	for (integer i=0; i<8; i=i+1) begin
	{A, B, C} = i;
	#20;
	end
$display("Done");
end
endmodule

SEM_3/DSD_LAB/Week1/lab3_tb.vcd
$date
	Wed Jul 31 16:12:18 2024
$end
$version
	Icarus Verilog
$end
$timescale
	1ns
$end
$scope module lab3_tb $end
$var wire 1 ! F2 $end
$var wire 1 " F1 $end
$var reg 1 # A $end
$var reg 1 $ B $end
$var reg 1 % C $end
$scope module l1 $end
$var wire 1 # A $end
$var wire 1 $ B $end
$var wire 1 % C $end
$var wire 1 " F1 $end
$var wire 1 ! F2 $end
$upscope $end
$scope begin $ivl_for_loop0 $end
$var integer 32 & i [31:0] $end
$upscope $end
$upscope $end
$enddefinitions $end
#0
$dumpvars
b0 &
0%
0$
0#
1"
1!
$end
#20
0!
0"
1%
b1 &
#40
0!
1$
0%
b10 &
#60
1"
1!
1%
b11 &
#80
1!
1#
0$
0%
b100 &
#100
0"
0!
1%
b101 &
#120
1"
1!
1$
0%
b110 &
#140
1%
b111 &
#160
b1000 &
