SEM_3/DSD_LAB/Week10/synchronous_counter.v
/*Q1 (Solved Exercise) - Design and write Verilog code for a three-bit counter that counts in the sequence 0, 1, 2, 4, 5, 6, 0 using JK flip-flops.*/
module jkff (Q, J, K, Reset, Clock);
  input J, K, Clock, Reset;
  output reg Q;
  always @ (posedge Clock or negedge Reset) begin
    case({J, K})
      2'b00:Q <= Q;
      2'b01:Q <= 1'b0;
      2'b10:Q <= 1'b1;
      2'b11:Q <= ~Q;
    endcase
    if (Reset==0)
      Q <= 0;
  end
endmodule

module synchronous_counter (clear, clk, Q);
  input clear, clk;
  output [2:0] Q;
  jkff FF0 (Q[0],~Q[1], 1'b1, clear, clk);
  jkff FF1 (Q[1], Q[0], 1'b1, clear, clk);
  jkff FF2 (Q[2], Q[1],Q[1],clear, clk);
endmodule

SEM_3/DSD_LAB/Week10/synchronous_counter_tb.v
`timescale 1ns/1ns
`include "synchronous_counter.v" //Name of the Verilog file
module synchronous_counter_tb ;
  reg clear, clk;
  wire [2:0] Q;
  synchronous_counter G0 (clear, clk, Q);
  always #5 clk=~clk;
  initial begin
    clear=0;  clk=1;
    #150 $finish;
  end
  initial begin
    $dumpfile("synchronous_counter_tb.vcd");
    $dumpvars(0,synchronous_counter_tb);
    $monitor($time, " clear=%b, Q=%3b", clear, Q );
    #12 clear =1;
  end
endmodule

SEM_3/DSD_LAB/Week10/synchronous_counter_tb.vcd
$date
	Wed Oct 23 14:24:32 2024
$end
$version
	Icarus Verilog
$end
$timescale
	1ns
$end
$scope module synchronous_counter_tb $end
$var wire 3 ! Q [2:0] $end
$var reg 1 " clear $end
$var reg 1 # clk $end
$scope module G0 $end
$var wire 1 " clear $end
$var wire 1 # clk $end
$var wire 3 $ Q [2:0] $end
$scope module FF0 $end
$var wire 1 # Clock $end
$var wire 1 % J $end
$var wire 1 & K $end
$var wire 1 " Reset $end
$var reg 1 ' Q $end
$upscope $end
$scope module FF1 $end
$var wire 1 # Clock $end
$var wire 1 ( J $end
$var wire 1 ) K $end
$var wire 1 " Reset $end
$var reg 1 * Q $end
$upscope $end
$scope module FF2 $end
$var wire 1 # Clock $end
$var wire 1 + J $end
$var wire 1 , K $end
$var wire 1 " Reset $end
$var reg 1 - Q $end
$upscope $end
$upscope $end
$upscope $end
$enddefinitions $end
#0
$dumpvars
0-
0,
0+
0*
1)
0(
0'
1&
1%
b0 $
1#
0"
b0 !
$end
#5
0#
#10
b0 !
b0 $
0'
1#
#12
1"
#15
0#
#20
1(
b1 !
b1 $
1'
1#
#25
0#
#30
0%
1+
1,
0(
1*
b10 !
b10 $
0'
1#
#35
0#
#40
1%
0+
0,
0*
b100 !
b100 $
1-
1#
#45
0#
#50
1(
b101 !
b101 $
1'
1#
#55
0#
#60
0%
0(
1+
1,
0'
b110 !
b110 $
1*
1#
#65
0#
#70
1%
0+
0,
0-
b0 !
b0 $
0*
1#
#75
0#
#80
1(
b1 !
b1 $
1'
1#
#85
0#
#90
0%
1+
1,
0(
1*
b10 !
b10 $
0'
1#
#95
0#
#100
1%
0+
0,
0*
b100 !
b100 $
1-
1#
#105
0#
#110
1(
b101 !
b101 $
1'
1#
#115
0#
#120
0%
0(
1+
1,
0'
b110 !
b110 $
1*
1#
#125
0#
#130
1%
0+
0,
0-
b0 !
b0 $
0*
1#
#135
0#
#140
1(
b1 !
b1 $
1'
1#
#145
0#
#150
0%
1+
1,
0(
1*
b10 !
b10 $
0'
1#
