SEM_3/DSD_LAB/Week3/Mux2to1.v
module Mux2to1 (w0, w1, s, f);
input w0, w1, s;
output f;
reg f;
always @(w0 or w1 or s)
f = s ? w1:w0;
endmodule

SEM_3/DSD_LAB/Week3/Mux8to1.v
/*Q2 - Write behavioral Verilog code for an 8 to 1 multiplexer using case statement. Use this along with a 2 to 1 multiplexer to write the hierarchical code for a 
16 to 1 multiplexer. */

module Mux8to1 (s, w, f);
input [0:2] s;
input [0:7] w;
output f;
reg g;
always@(*)
begin
case(s)
  3'b000:g=w[0];
  3'b001:g=w[1];
  3'b010:g=w[2];
  3'b011:g=w[3];
  3'b100:g=w[4];
  3'b101:g=w[5];
  3'b110:g=w[6];
  3'b111:g=w[7];
endcase
end
assign f = g;
endmodule

SEM_3/DSD_LAB/Week3/Mux16to1.v
`include "Mux8to1.v"
`include "Mux2to1.v"
module Mux16to1 (s, w, f);
input [3:0] s;
input [15:0] w;
output f;
wire g, h, i;
Mux8to1 m1(s[2:0], w[7:0], g);
Mux8to1 m2(s[2:0], w[15:8], h);
Mux2to1 m3(g, h, s[3], f);
//assign f=i;
endmodule

SEM_3/DSD_LAB/Week3/Mux16to1_tb.v
//Test bench
`timescale 1ns/1ns
`include "Mux16to1.v"
module Mux16to1_tb ();
reg [3:0] s;
reg [15:0] w;
wire f;
Mux16to1 mu(s, w, f);
initial
begin
 $dumpfile("Mux16to1_tb.vcd");
 $dumpvars(0, Mux16to1_tb);
 w = 16'b1010101010101010;
 for (integer i=0; i<16; i++)
 begin
   {s} = i;
   #10;
 end
 $display("Done");
end
endmodule

SEM_3/DSD_LAB/Week3/Mux16to1_tb.vcd
$date
	Wed Aug 21 14:20:58 2024
$end
$version
	Icarus Verilog
$end
$timescale
	1ns
$end
$scope module Mux16to1_tb $end
$var wire 1 ! f $end
$var reg 4 " s [3:0] $end
$var reg 16 # w [15:0] $end
$scope module mu $end
$var wire 4 $ s [3:0] $end
$var wire 16 % w [15:0] $end
$var wire 1 & h $end
$var wire 1 ' g $end
$var wire 1 ! f $end
$scope module m1 $end
$var wire 1 ' f $end
$var wire 3 ( s [0:2] $end
$var wire 8 ) w [0:7] $end
$var reg 1 * g $end
$upscope $end
$scope module m2 $end
$var wire 1 & f $end
$var wire 3 + s [0:2] $end
$var wire 8 , w [0:7] $end
$var reg 1 - g $end
$upscope $end
$scope module m3 $end
$var wire 1 . s $end
$var wire 1 ' w0 $end
$var wire 1 & w1 $end
$var reg 1 ! f $end
$upscope $end
$upscope $end
$scope begin $ivl_for_loop0 $end
$var integer 32 / i [31:0] $end
$upscope $end
$upscope $end
$enddefinitions $end
#0
$dumpvars
b0 /
0.
1-
b10101010 ,
b0 +
1*
b10101010 )
b0 (
1'
1&
b1010101010101010 %
b0 $
b1010101010101010 #
b0 "
1!
$end
#10
0!
0'
0*
0&
0-
b1 (
b1 +
b1 "
b1 $
b1 /
#20
1!
1'
1*
1&
1-
b10 (
b10 +
b10 "
b10 $
b10 /
#30
0!
0'
0*
0&
0-
b11 (
b11 +
b11 "
b11 $
b11 /
#40
1!
1'
1*
1&
1-
b100 (
b100 +
b100 "
b100 $
b100 /
#50
0!
0'
0*
0&
0-
b101 (
b101 +
b101 "
b101 $
b101 /
#60
1!
1'
1*
1&
1-
b110 (
b110 +
b110 "
b110 $
b110 /
#70
0!
0'
0*
0&
0-
b111 (
b111 +
b111 "
b111 $
b111 /
#80
1!
1'
1*
1&
1-
b0 (
b0 +
1.
b1000 "
b1000 $
b1000 /
#90
0!
0'
0*
0&
0-
b1 (
b1 +
b1001 "
b1001 $
b1001 /
#100
1!
1'
1*
1&
1-
b10 (
b10 +
b1010 "
b1010 $
b1010 /
#110
0!
0'
0*
0&
0-
b11 (
b11 +
b1011 "
b1011 $
b1011 /
#120
1!
1'
1*
1&
1-
b100 (
b100 +
b1100 "
b1100 $
b1100 /
#130
0!
0'
0*
0&
0-
b101 (
b101 +
b1101 "
b1101 $
b1101 /
#140
1!
1'
1*
1&
1-
b110 (
b110 +
b1110 "
b1110 $
b1110 /
#150
0!
0'
0*
0&
0-
b111 (
b111 +
b1111 "
b1111 $
b1111 /
#160
b10000 /
