SEM_3/DSD_LAB/Week2/lab0.v
/*Apply functional decomposition for the following function to obtain a simplified circuit and
simulate using Verilog.*/
module lab0 (x1, x2, x3, x4, f);
input x1, x2, x3, x4;
output f;
assign g = (x1 & ~x2) | (~x1 & x2);
assign f = (g & x3) | (~g & x4);
endmodule

SEM_3/DSD_LAB/Week2/lab0_tb.v
//Test bench
`timescale 1ns/1ns
`include "lab0.v"
module lab0_tb ();
reg x1, x2, x3, x4;
wire f;
lab0 l (x1, x2, x3, x4, f);
initial
begin
$dumpfile("lab0_tb.vcd");
$dumpvars(0, lab0_tb);
for (integer i = 0; i<16; i++)
begin
{x1, x2, x3, x4} = i;
#20;
end
$display("Done");
end
endmodule

SEM_3/DSD_LAB/Week2/lab0_tb.vcd
$date
	Wed Aug  7 14:21:39 2024
$end
$version
	Icarus Verilog
$end
$timescale
	1ns
$end
$scope module lab0_tb $end
$var wire 1 ! f $end
$var reg 1 " x1 $end
$var reg 1 # x2 $end
$var reg 1 $ x3 $end
$var reg 1 % x4 $end
$scope module l $end
$var wire 1 ! f $end
$var wire 1 & g $end
$var wire 1 " x1 $end
$var wire 1 # x2 $end
$var wire 1 $ x3 $end
$var wire 1 % x4 $end
$upscope $end
$scope begin $ivl_for_loop0 $end
$var integer 32 ' i [31:0] $end
$upscope $end
$upscope $end
$enddefinitions $end
#0
$dumpvars
b0 '
0&
0%
0$
0#
0"
0!
$end
#20
1!
1%
b1 '
#40
0!
1$
0%
b10 '
#60
1!
1%
b11 '
#80
1&
0!
1#
0$
0%
b100 '
#100
1%
b101 '
#120
1!
1$
0%
b110 '
#140
1%
b111 '
#160
0!
1"
0#
0$
0%
b1000 '
#180
1%
b1001 '
#200
1!
1$
0%
b1010 '
#220
1%
b1011 '
#240
0&
0!
1#
0$
0%
b1100 '
#260
1!
1%
b1101 '
#280
0!
1$
0%
b1110 '
#300
1!
1%
b1111 '
#320
b10000 '
