SEM_3/DSD_LAB/Week6/AJKFF.v
/*Q3 - Write behavioral Verilog code for a positive edge-triggered JK FF with asynchronous active high reset.*/
module AJKFF (J, K, Clock , Reset, Q);
  input J, K, Clock, Reset;
  output reg Q;
  
  always @ (posedge Clock) begin
    case({J, K})
      2'b00:Q <= Q;
      2'b01:Q <= 1'b0;
      2'b10:Q <= 1'b1;
      2'b11:Q <= ~Q;
    endcase
  end
  
  always @ (posedge Clock or negedge Clock) begin
    if (Reset)
      Q <= 0;
  end
endmodule

SEM_3/DSD_LAB/Week6/AJKFF_tb.v
//Test bench
`timescale 1ns/1ns
`include "AJKFF.v"
module AJKFF_tb ();
  reg J, K, Clock, Reset;
  wire Q;
  AJKFF f1(J, K, Clock, Reset, Q);
  initial begin
    $dumpfile("AJKFF_tb.vcd");
    $dumpvars(0, AJKFF_tb);
    Clock = 0;
    forever #10 Clock = ~Clock;
  end
  initial begin
    for (integer i=0; i<8; i++)
      begin
       {Reset, J, K} = i;
       #20;
      end
    $display("Done");    
    $finish;
  end
endmodule

SEM_3/DSD_LAB/Week6/AJKFF_tb.vcd
$date
	Wed Sep  4 15:52:40 2024
$end
$version
	Icarus Verilog
$end
$timescale
	1ns
$end
$scope module AJKFF_tb $end
$var wire 1 ! Q $end
$var reg 1 " Clock $end
$var reg 1 # J $end
$var reg 1 $ K $end
$var reg 1 % Reset $end
$scope module f1 $end
$var wire 1 " Clock $end
$var wire 1 # J $end
$var wire 1 $ K $end
$var wire 1 % Reset $end
$var reg 1 ! Q $end
$upscope $end
$scope begin $ivl_for_loop0 $end
$var integer 32 & i [31:0] $end
$upscope $end
$upscope $end
$enddefinitions $end
#0
$dumpvars
b0 &
0%
0$
0#
0"
x!
$end
#10
1"
#20
0"
1$
b1 &
#30
0!
1"
#40
0"
1#
0$
b10 &
#50
1!
1"
#60
0"
1$
b11 &
#70
0!
1"
#80
0"
1%
0#
0$
b100 &
#90
1"
#100
0"
1$
b101 &
#110
1"
#120
0"
1#
0$
b110 &
#130
0!
1"
#140
0"
1$
b111 &
#150
0!
1"
#160
0"
b1000 &
