SEM_3/DSD_LAB/Week6/DFF.v
/*Q1 - Write behavioral Verilog code for a positive edge-triggered D FF with synchronous active high reset.*/
module DFF (D, Clock , Reset, Q);
  input D, Clock, Reset;
  output reg Q;
  always @ (posedge Clock)
  if (Reset)
    Q <= 0;
  else
    Q<=D;
endmodule

SEM_3/DSD_LAB/Week6/DFF_tb.v
//Test bench
`timescale 1ns/1ns
`include "DFF.v"
module DFF_tb ();
  reg D, Clock, Reset;
  wire Q;
  DFF f1(D, Clock, Reset, Q);
  initial begin
    $dumpfile("DFF_tb.vcd");
    $dumpvars(0, DFF_tb);
    Clock = 0;
    forever #10 Clock = ~Clock;
  end
  initial begin
    for (integer i=0; i<4; i++)
      begin
       {Reset, D} = i;
       #20;
      end
    $display("Done");    
    $finish;
  end
endmodule

SEM_3/DSD_LAB/Week6/DFF_tb.vcd
$date
	Wed Sep  4 14:34:12 2024
$end
$version
	Icarus Verilog
$end
$timescale
	1ns
$end
$scope module DFF_tb $end
$var wire 1 ! Q $end
$var reg 1 " Clock $end
$var reg 1 # D $end
$var reg 1 $ Reset $end
$scope module f1 $end
$var wire 1 " Clock $end
$var wire 1 # D $end
$var wire 1 $ Reset $end
$var reg 1 ! Q $end
$upscope $end
$scope begin $ivl_for_loop0 $end
$var integer 32 % i [31:0] $end
$upscope $end
$upscope $end
$enddefinitions $end
#0
$dumpvars
b0 %
0$
0#
0"
x!
$end
#10
0!
1"
#20
0"
1#
b1 %
#30
1!
1"
#40
0"
1$
0#
b10 %
#50
0!
1"
#60
0"
1#
b11 %
#70
1"
#80
0"
b100 %
